humanml/__init__.py
humanml/api.py
humanml/auto_logger.py
humanml/data_preprocessor.py
humanml/data_splitter.py
humanml/ensemble.py
humanml/hyperparameter_tuner.py
humanml/model_evaluator.py
humanml/model_explainer.py
humanml/model_exporter.py
humanml/model_selector.py
humanml/model_trainer.py
humanml/plot_utilities.py
humanml/preprocessor.py
humanml/report_generator.py
humanml/rl_optimizer.py
humanml-0.3.1.dist-info/licenses/LICENSE
humanml-0.3.1.dist-info/METADATA
humanml-0.3.1.dist-info/WHEEL
humanml-0.3.1.dist-info/top_level.txt
humanml-0.3.1.dist-info/RECORD
